lalian/__init__.py
lalian/__main__.py
lalian/constants.py
lalian/package.py
lalian-0.1.1.dist-info/entry_points.txt
lalian-0.1.1.dist-info/LICENSE
lalian-0.1.1.dist-info/METADATA
lalian-0.1.1.dist-info/WHEEL
lalian-0.1.1.dist-info/RECORD
