Metadata-Version: 2.1
Name: lalian
Version: 0.1.1
Summary: Create a pseudo-executable with embedded Python code using zipimport.
License: GNU General Public License v3 (GPLv3)
Author: Koutaro Mukai
Author-email: mukai.k1011k@outlook.jp
Requires-Python: >=3.9,<4.0
Classifier: License :: Other/Proprietary License
Classifier: Programming Language :: Python :: 3
Classifier: Programming Language :: Python :: 3.9
Classifier: Programming Language :: Python :: 3.10
Classifier: Programming Language :: Python :: 3.11
Classifier: Programming Language :: Python :: 3.12
